MuditJain/TopsisMuditJain101903673.py
MuditJain/__init__.py
Topsis_MuditJain-0.0.0.dist-info/License
Topsis_MuditJain-0.0.0.dist-info/METADATA
Topsis_MuditJain-0.0.0.dist-info/WHEEL
Topsis_MuditJain-0.0.0.dist-info/top_level.txt
Topsis_MuditJain-0.0.0.dist-info/RECORD
