Metadata-Version: 2.1
Name: Topsis-MuditJain
Version: 0.0.0
Summary: Topsis
Author: Mudit Jain
Author-email: jainmudit67890.md@gmail.com
License: UNKNOWN
Keywords: python,topsis
Platform: UNKNOWN
Classifier: Development Status :: 1 - Planning
Classifier: Intended Audience :: Developers
Classifier: Programming Language :: Python :: 3
Classifier: Operating System :: Unix
Classifier: Operating System :: MacOS :: MacOS X
Classifier: Operating System :: Microsoft :: Windows
License-File: License
